python_vault/__init__.py
python_vault/vault.py
python_vault-0.0.3.dist-info/licenses/LICENSE
python_vault-0.0.3.dist-info/METADATA
python_vault-0.0.3.dist-info/WHEEL
python_vault-0.0.3.dist-info/top_level.txt
python_vault-0.0.3.dist-info/RECORD
