Metadata-Version: 2.4
Name: python-vault
Version: 0.0.3
Summary: A Python client for HashiCorp Vault with AppRole authentication and secret management.
Home-page: https://github.com/aviz92/python-vault
Author: Avi Zaguri
Author-email: 
Project-URL: Repository, https://github.com/aviz92/python-vault
Requires-Python: >=3.11
License-File: LICENSE
Requires-Dist: setuptools
Requires-Dist: wheel
Requires-Dist: python-dotenv
Requires-Dist: pre-commit
Requires-Dist: colorlog
Requires-Dist: pytest
Requires-Dist: pytest-rerunfailures
Requires-Dist: hvac
Requires-Dist: custom_python_logger
Dynamic: author
Dynamic: description
Dynamic: description-content-type
Dynamic: home-page
Dynamic: license-file
Dynamic: project-url
Dynamic: requires-dist
Dynamic: requires-python
Dynamic: summary
